[
    {
        "kind": "youtube#video",
        "etag": "FXJDDwmDaVMb6yhllhH18g98sAk",
        "id": "zXcPjzZSZLE",
        "snippet": {
            "publishedAt": "2020-09-30T19:40:52Z",
            "channelId": "UCQiojTHkAvFvdCSajklqUXA",
            "title": "Among Us but we troll people in PUBLIC LOBBIES and MAKE THEM GO INSANE!",
            "description": "Become a member of the channel and gain access to the Terroriser Discord and also custom emotes in livestreams here: https://www.youtube.com/channel/UCQiojTHkAvFvdCSajklqUXA/join\n\nIf you enjoyed the video hit that LIKE button and drop a COMMENT down below!\n\nStay Awesome guys!\n\nWant a Terroriser T-Shirt? Check them out here: \nhttps://shop.terrorisermerch.com/\nhttps://terroriser.3blackdot.com/\n\nPlease behave in the comments section and avoid silly or hateful comments :D\n\n►►►Follow me on Twitter◄◄◄ \nhttps://twitter.com/Terroriser\n\n►►►Like me on Facebook◄◄◄ https://www.facebook.com/pages/Terroriser\n\n►►►Follow me on Twitch◄◄◄\nhttp://www.twitch.tv/Terroriser\n\n►►►Follow me on Instagram◄◄◄\nhttp://instagram.com/Terroriser\n\nFriends in the Video\nMoo Snuckel: https://www.youtube.com/user/BnBENTERPR1SES\nVanoss:  https://www.youtube.com/user/VanossGaming\nDaithi: https://www.youtube.com/user/DaithiDeNogla\nWildcat: https://www.youtube.com/user/W1LDC4T43",
            "thumbnails": {
                "default": {
                    "url": "https://i.ytimg.com/vi/zXcPjzZSZLE/default.jpg",
                    "width": 120,
                    "height": 90
                },
                "medium": {
                    "url": "https://i.ytimg.com/vi/zXcPjzZSZLE/mqdefault.jpg",
                    "width": 320,
                    "height": 180
                },
                "high": {
                    "url": "https://i.ytimg.com/vi/zXcPjzZSZLE/hqdefault.jpg",
                    "width": 480,
                    "height": 360
                },
                "standard": {
                    "url": "https://i.ytimg.com/vi/zXcPjzZSZLE/sddefault.jpg",
                    "width": 640,
                    "height": 480
                },
                "maxres": {
                    "url": "https://i.ytimg.com/vi/zXcPjzZSZLE/maxresdefault.jpg",
                    "width": 1280,
                    "height": 720
                }
            },
            "channelTitle": "Terroriser",
            "tags": [
                "among us",
                "video games",
                "among us gameplay",
                "among us twitch",
                "among us impostor",
                "among us funny",
                "among us funny moments",
                "terrorizer",
                "the terroriser",
                "terroriser",
                "multiplayer",
                "glitches",
                "funny moments",
                "comedy",
                "irish",
                "goofy",
                "hilarious moments",
                "fails",
                "nogla",
                "brian",
                "secret",
                "humor",
                "silly",
                "parody",
                "funny gaming",
                "funny gameplay",
                "among us game",
                "among us imposter",
                "among us with friends",
                "gaming",
                "trending",
                "AMONG US PUBLIC LOBBY",
                "AMONG US TROLLING",
                "AMONG US PUBLIC LOBBIES",
                "AMONG US MEMES"
            ],
            "categoryId": "20",
            "liveBroadcastContent": "none",
            "defaultLanguage": "en",
            "localized": {
                "title": "Among Us but we troll people in PUBLIC LOBBIES and MAKE THEM GO INSANE!",
                "description": "Become a member of the channel and gain access to the Terroriser Discord and also custom emotes in livestreams here: https://www.youtube.com/channel/UCQiojTHkAvFvdCSajklqUXA/join\n\nIf you enjoyed the video hit that LIKE button and drop a COMMENT down below!\n\nStay Awesome guys!\n\nWant a Terroriser T-Shirt? Check them out here: \nhttps://shop.terrorisermerch.com/\nhttps://terroriser.3blackdot.com/\n\nPlease behave in the comments section and avoid silly or hateful comments :D\n\n►►►Follow me on Twitter◄◄◄ \nhttps://twitter.com/Terroriser\n\n►►►Like me on Facebook◄◄◄ https://www.facebook.com/pages/Terroriser\n\n►►►Follow me on Twitch◄◄◄\nhttp://www.twitch.tv/Terroriser\n\n►►►Follow me on Instagram◄◄◄\nhttp://instagram.com/Terroriser\n\nFriends in the Video\nMoo Snuckel: https://www.youtube.com/user/BnBENTERPR1SES\nVanoss:  https://www.youtube.com/user/VanossGaming\nDaithi: https://www.youtube.com/user/DaithiDeNogla\nWildcat: https://www.youtube.com/user/W1LDC4T43"
            },
            "defaultAudioLanguage": "en-GB"
        }
    }
]